gibbs_sampler/__init__.py
gibbs_sampler/example_seqs.fa
gibbs_sampler/gibbs_sampler.py
gibbs_sampler-0.2.0.dist-info/entry_points.txt
gibbs_sampler-0.2.0.dist-info/LICENSE
gibbs_sampler-0.2.0.dist-info/WHEEL
gibbs_sampler-0.2.0.dist-info/METADATA
gibbs_sampler-0.2.0.dist-info/RECORD
