Metadata-Version: 2.1
Name: gibbs-sampler
Version: 0.2.0
Summary: Gibbs Sampler for motif discovery
License: CC0 v1.0 Universal
Author: Monty Python
Requires-Python: >=3.8,<4.0
Classifier: License :: Other/Proprietary License
Classifier: Programming Language :: Python :: 3
Classifier: Programming Language :: Python :: 3.10
Classifier: Programming Language :: Python :: 3.8
Classifier: Programming Language :: Python :: 3.9
Requires-Dist: bio (>=1.3.3,<2.0.0)
Requires-Dist: numpy (>=1.22.3,<2.0.0)
Requires-Dist: weblogo (>=3.7.9,<4.0.0)
